mcp_jira_confluence/__init__.py
mcp_jira_confluence/config.py
mcp_jira_confluence/confluence.py
mcp_jira_confluence/formatter.py
mcp_jira_confluence/jira.py
mcp_jira_confluence/models.py
mcp_jira_confluence/server.py
mcp_jira_confluence-0.2.10.dist-info/METADATA
mcp_jira_confluence-0.2.10.dist-info/WHEEL
mcp_jira_confluence-0.2.10.dist-info/entry_points.txt
mcp_jira_confluence-0.2.10.dist-info/licenses/LICENSE
mcp_jira_confluence-0.2.10.dist-info/RECORD
