Metadata-Version: 2.4
Name: mcp-jira-confluence
Version: 0.2.10
Summary: Model Context Protocol server for Jira and Confluence
Project-URL: Homepage, https://github.com/akhilthomas236/mcp-jira-confluence
Project-URL: Repository, https://github.com/akhilthomas236/mcp-jira-confluence
Project-URL: Issues, https://github.com/akhilthomas236/mcp-jira-confluence/issues
Project-URL: Documentation, https://github.com/akhilthomas236/mcp-jira-confluence/blob/main/README.md
Author-email: akhilthomas236 <akhilthomas236@gmail.com>
License: MIT
License-File: LICENSE
Keywords: atlassian,confluence,jira,mcp,model-context-protocol
Classifier: Development Status :: 4 - Beta
Classifier: Intended Audience :: Developers
Classifier: License :: OSI Approved :: MIT License
Classifier: Programming Language :: Python :: 3
Classifier: Programming Language :: Python :: 3.12
Classifier: Topic :: Communications :: Chat
Classifier: Topic :: Office/Business :: Groupware
Classifier: Topic :: Software Development :: Libraries :: Python Modules
Requires-Python: >=3.12
Requires-Dist: httpx>=0.24.0
Requires-Dist: mcp>=1.9.4
Requires-Dist: pydantic>=2.0.0
